satosa_oidcop/__init__.py
satosa_oidcop/idpy_oidcop.py
satosa_oidcop/__pycache__/__init__.cpython-310.pyc
satosa_oidcop/__pycache__/idpy_oidcop.cpython-310.pyc
satosa_oidcop/core/__init__.py
satosa_oidcop/core/application.py
satosa_oidcop/core/claims.py
satosa_oidcop/core/response.py
satosa_oidcop/core/user_authn.py
satosa_oidcop/core/user_info.py
satosa_oidcop/core/__pycache__/__init__.cpython-310.pyc
satosa_oidcop/core/__pycache__/application.cpython-310.pyc
satosa_oidcop/core/__pycache__/claims.cpython-310.pyc
satosa_oidcop/core/__pycache__/response.cpython-310.pyc
satosa_oidcop/core/__pycache__/user_authn.cpython-310.pyc
satosa_oidcop/core/__pycache__/user_info.cpython-310.pyc
satosa_oidcop/core/storage/__init__.py
satosa_oidcop/core/storage/base.py
satosa_oidcop/core/storage/mongo.py
satosa_oidcop/core/storage/__pycache__/__init__.cpython-310.pyc
satosa_oidcop/core/storage/__pycache__/base.cpython-310.pyc
satosa_oidcop/core/storage/__pycache__/mongo.cpython-310.pyc
satosa_oidcop-4.0.0.dist-info/licenses/LICENSE
satosa_oidcop-4.0.0.dist-info/METADATA
satosa_oidcop-4.0.0.dist-info/WHEEL
satosa_oidcop-4.0.0.dist-info/top_level.txt
satosa_oidcop-4.0.0.dist-info/RECORD
