Metadata-Version: 2.4
Name: satosa_oidcop
Version: 4.0.0
Summary: SATOSA Frontend based on idetity python oidcop
Home-page: https://github.com/UniversitaDellaCalabria/satosa-oidcop
Author: Giuseppe De Marco
Author-email: giuseppe.demarco@unical.it
License: License :: OSI Approved :: GNU Affero General Public License v3
Classifier: Development Status :: 5 - Production/Stable
Classifier: License :: OSI Approved :: GNU Affero General Public License v3
Classifier: Programming Language :: Python :: 3
Classifier: Programming Language :: Python :: 3 :: Only
Classifier: Programming Language :: Python :: 3.9
Classifier: Programming Language :: Python :: 3.10
Classifier: Programming Language :: Python :: 3.11
License-File: LICENSE
Requires-Dist: satosa>=8.0.0
Requires-Dist: pymongo<5.0,>=3.11
Requires-Dist: idpyoidc<4.2.0,>=4.1.0
Dynamic: author
Dynamic: author-email
Dynamic: classifier
Dynamic: description
Dynamic: description-content-type
Dynamic: home-page
Dynamic: license
Dynamic: license-file
Dynamic: requires-dist
Dynamic: summary
